mycalc/calculator.py
oss0-0.0.1.dist-info/METADATA
oss0-0.0.1.dist-info/WHEEL
oss0-0.0.1.dist-info/top_level.txt
oss0-0.0.1.dist-info/RECORD
