Metadata-Version: 2.1
Name: oss0
Version: 0.0.1
Summary: calculater3
Home-page: https://github.com/chunsejin/calc0001
Download-URL: https://github.com/chunsejin/calc0001
Author: jeong won
License: UNKNOWN
Platform: UNKNOWN
Classifier: Programming Language :: Python :: 3
